pypfeiffervacuumhighscrollprotocol/__init__.py
pypfeiffervacuumhighscrollprotocol/pyPfeifferVacuumHighscrollProtocol.py
pypfeiffervacuumhighscrollprotocol-0.0.1.dist-info/licenses/LICENCE
pypfeiffervacuumhighscrollprotocol-0.0.1.dist-info/METADATA
pypfeiffervacuumhighscrollprotocol-0.0.1.dist-info/WHEEL
pypfeiffervacuumhighscrollprotocol-0.0.1.dist-info/top_level.txt
pypfeiffervacuumhighscrollprotocol-0.0.1.dist-info/RECORD
