Metadata-Version: 2.4
Name: pypfeiffervacuumhighscrollprotocol
Version: 0.0.1
Summary: Pfeiffer Vacuum HighScroll Protocol helpers
Author-email: Enno Henn <henn@ipfdd.de>
Requires-Python: >=3.8
License-File: LICENCE
Dynamic: license-file
